frp.py
frpc.py
frps.py
setup.py
nodemcu.egg-info/PKG-INFO
nodemcu.egg-info/SOURCES.txt
nodemcu.egg-info/dependency_links.txt
nodemcu.egg-info/entry_points.txt
nodemcu.egg-info/top_level.txt